setup.py
powny_cli.egg-info/PKG-INFO
powny_cli.egg-info/SOURCES.txt
powny_cli.egg-info/dependency_links.txt
powny_cli.egg-info/entry_points.txt
powny_cli.egg-info/requires.txt
powny_cli.egg-info/top_level.txt
pownycli/__init__.py
pownycli/client.py
pownycli/config.yaml
pownycli/gitapi.py
pownycli/pownyapi.py
pownycli/settings.py
pownycli/util.py