Metadata-Version: 1.0
Name: powny-cli
Version: 0.10.0
Summary: Powny command line tool
Home-page: https://github.com/yandex-sysmon/powny-cli
Author: Alexander Kushnarev
Author-email: avkushnarev@gmail.com
License: UNKNOWN
Platform: UNKNOWN
